treinta_redshift/__init__.py
treinta_redshift/core.py
treinta_redshift-1.6.dist-info/LICENSE
treinta_redshift-1.6.dist-info/METADATA
treinta_redshift-1.6.dist-info/WHEEL
treinta_redshift-1.6.dist-info/top_level.txt
treinta_redshift-1.6.dist-info/RECORD
