Metadata-Version: 2.1
Name: treinta_redshift
Version: 1.6
Summary: paquete que permite interactuar pandas con redshift
Author: cristian.pinela
Author-email: cristian.pinela@treinta.co
License: LICENSE
License-File: LICENSE
Requires-Dist: boto3
Requires-Dist: botocore
Requires-Dist: numpy
Requires-Dist: pandas
Requires-Dist: pyarrow
